nerif/__init__.py
nerif/batch/__init__.py
nerif/batch/batch.py
nerif/batch/file.py
nerif/cli/__init__.py
nerif/cli/compress_image.py
nerif/core/__init__.py
nerif/core/core.py
nerif/model/__init__.py
nerif/model/audio_model.py
nerif/model/model.py
nerif/model/vision_model_enhanced.py
nerif/utils/__init__.py
nerif/utils/format.py
nerif/utils/image_compress.py
nerif/utils/log.py
nerif/utils/token_counter.py
nerif/utils/utils.py
nerif-0.10.1.dist-info/METADATA
nerif-0.10.1.dist-info/WHEEL
nerif-0.10.1.dist-info/licenses/LICENSE
nerif-0.10.1.dist-info/RECORD
