Metadata-Version: 2.4
Name: nerif
Version: 0.10.1
Summary: LLM powered Python
Project-URL: Homepage, https://github.com/Nerif-AI/nerif
Author: Chivier Humber
License:                     GNU GENERAL PUBLIC LICENSE
License-File: LICENSE
Keywords: feed,reader,tutorial
Classifier: License :: OSI Approved :: GNU General Public License v3 (GPLv3)
Classifier: Programming Language :: Python
Classifier: Programming Language :: Python :: 3
Requires-Python: >=3.8
Requires-Dist: httpx
Requires-Dist: litellm
Requires-Dist: numpy
Requires-Dist: openai
Requires-Dist: pillow>=9.0.0
Requires-Dist: prettytable
Requires-Dist: python-dotenv
Requires-Dist: requests
Provides-Extra: dev
Requires-Dist: bumpver; extra == 'dev'
Requires-Dist: ipython; extra == 'dev'
Requires-Dist: isort; extra == 'dev'
Requires-Dist: pip-tools; extra == 'dev'
Requires-Dist: pytest; extra == 'dev'
Requires-Dist: ruff; extra == 'dev'
Provides-Extra: image
Requires-Dist: pillow>=9.0.0; extra == 'image'
